robot_status_cli/__init__.py
robot_status_cli/base.py
robot_status_cli/client.py
robot_status_cli-0.3.0.dist-info/METADATA
robot_status_cli-0.3.0.dist-info/WHEEL
robot_status_cli-0.3.0.dist-info/top_level.txt
robot_status_cli-0.3.0.dist-info/RECORD
