Metadata-Version: 2.1
Name: robot-status-cli
Version: 0.3.0
Summary: cli and auth for robot status
Home-page: UNKNOWN
Author: leonardoo
Author-email: leonardoorozcop@gmail.com
License: MIT
Platform: UNKNOWN
Classifier: Development Status :: 3 - Alpha
Classifier: Intended Audience :: Developers
Classifier: Programming Language :: Python
Classifier: Programming Language :: Python :: 3
Classifier: Programming Language :: Python :: 3.5
Classifier: Programming Language :: Python :: 3.6
Classifier: Programming Language :: Python :: 3.7
Requires-Dist: requests (==2.13.0)
Requires-Dist: cryptography (>=2.3)
